abstract_builder/__init__.py
abstract_builder/blocks.py
abstract_builder/cmd.py
abstract_builder/expfile.py
abstract_builder/interpretator.py
abstract_builder/loger.py
abstract_builder/main.py
abstract_builder/static/main.js
abstract_builder/static/style.css
abstract_builder-1.0.1.dist-info/LICENSE
abstract_builder-1.0.1.dist-info/METADATA
abstract_builder-1.0.1.dist-info/WHEEL
abstract_builder-1.0.1.dist-info/entry_points.txt
abstract_builder-1.0.1.dist-info/top_level.txt
abstract_builder-1.0.1.dist-info/RECORD
