Metadata-Version: 2.1
Name: abstract-builder
Version: 1.0.1
Summary: Преобразование конспектов в HTML-документы
Home-page: https://github.com/FullDungeon/abstract_builder
Author: FullDungeon
Author-email: ddd.dungeon@gmail.com
License: UNKNOWN
Platform: UNKNOWN
Classifier: Programming Language :: Python :: 3.8
Classifier: License :: OSI Approved :: MIT License
Classifier: Operating System :: OS Independent
Requires-Python: >=3.8
License-File: LICENSE
Requires-Dist: importlib-resources
